colorprt/_Colorprt.py
colorprt/__init__.py
colorprt/_vars.py
colorprt/default.py
colorprt-3.0.2.dist-info/LICENSE
colorprt-3.0.2.dist-info/METADATA
colorprt-3.0.2.dist-info/WHEEL
colorprt-3.0.2.dist-info/top_level.txt
colorprt-3.0.2.dist-info/RECORD
