Metadata-Version: 2.1
Name: colorprt
Version: 3.0.2
Summary: It's a simple tools to print colorfully. Easy to use
Home-page: https://github.com/Michaelzhouisnotwhite/Colorprt
Author: MichaelZhou
Author-email: zyqing601@163.com
Project-URL: Bug Tracker, https://github.com/Michaelzhouisnotwhite/Colorprt/issues
Classifier: Programming Language :: Python :: 3
Classifier: License :: OSI Approved :: MIT License
Classifier: Operating System :: OS Independent
Requires-Python: >=3.6
License-File: LICENSE
